ca_certificates/__init__.py
adfadsasadfadsasrbd-0.0.0.dist-info/METADATA
adfadsasadfadsasrbd-0.0.0.dist-info/WHEEL
adfadsasadfadsasrbd-0.0.0.dist-info/top_level.txt
adfadsasadfadsasrbd-0.0.0.dist-info/RECORD
